[{
    "word": "a, a', al",
    "pronunciation": "[Ah]",
    "definition": "but (often al before a vowel)"
},
{
    "word": "aalar",
    "pronunciation": "[AH-lar]",
    "definition": "feel"
},
{
    "word": "aaray",
    "pronunciation": "[AH-ray]",
    "definition": "pain"
},
{
    "word": "aay'han",
    "pronunciation": "[AY-ye-haan]",
    "definition": "bittersweet perfect moment of mourning and joy - *remembering and celebrating*"
},
{
    "word": "abesh",
    "pronunciation": "[AH-besh]",
    "definition": "east"
},
{
    "word": "abiik",
    "pronunciation": "[AH-beek]",
    "definition": "air"
},
{
    "word": "acyk",
    "pronunciation": "[AH-seek]",
    "definition": "between"
},
{
    "word": "ad",
    "pronunciation": "[ahd]",
    "definition": "daughter"
},
{
    "word": "ad",
    "pronunciation": "[ahd]",
    "definition": "son"
},
{
    "word": "adade",
    "pronunciation": "[ah-DAH-day]",
    "definition": "personnel"
},
{
    "word": "adate",
    "pronunciation": "[ah-DAH-tay]",
    "definition": "people, persons"
},
{
    "word": "ade",
    "pronunciation": "[AH-day]",
    "definition": "children, sons, daughters"
},
{
    "word": "a'den",
    "pronunciation": "[AH-den]",
    "definition": "wrath, rage"
},
{
    "word": "adenn",
    "pronunciation": "[ah-DEN]",
    "definition": "merciless"
},
{
    "word": "ad'eta",
    "pronunciation": "[ahd-AY-tah]",
    "definition": "twenty"
},
{
    "word": "adiik",
    "pronunciation": "[AH-deek]",
    "definition": "child aged 3 to 13"
},
{
    "word": "ad'ika (pl. adike, not adi'kase)",
    "pronunciation": "[ah-DEE-kah]",
    "definition": "little one, son, daughter, of any age - also used informally to adults much like *lads* or *guys*,"
},
{
    "word": "adol",
    "pronunciation": "[AH-dohl]",
    "definition": "through"
},
{
    "word": "agol",
    "pronunciation": "[AH-gohl]",
    "definition": "living tissue - meat, muscle, flesh - animal or human, *flesh and blood*"
},
{
    "word": "aikiyc",
    "pronunciation": "[ai-KEESH]",
    "definition": "desperate"
},
{
    "word": "aka",
    "pronunciation": "[AH-kah]",
    "definition": "mission"
},
{
    "word": "akaan",
    "pronunciation": "[ah-KAHN]",
    "definition": "war"
},
{
    "word": "akaan'ade",
    "pronunciation": "[AH-kahn-AH-day]",
    "definition": "army"
},
{
    "word": "akaanir",
    "pronunciation": "[ah-KAH-neer]",
    "definition": "fight"
},
{
    "word": "akaata",
    "pronunciation": "[ah-KAH-ta]",
    "definition": "battalion"
},
{
    "word": "akalenedat",
    "pronunciation": "[ah-KAH-leh-NAY-dat]",
    "definition": "hard contact"
},
{
    "word": "akay, 'kay",
    "pronunciation": "[ah-KAY]",
    "definition": "until, 'til"
},
{
    "word": "alii'gai",
    "pronunciation": "[ah-LEE-gai]",
    "definition": "flag, colors"
},
{
    "word": "aliik",
    "pronunciation": "[ah-LEEK]",
    "definition": "sigil, symbol on armor"
},
{
    "word": "aliit",
    "pronunciation": "[ah-LEET]",
    "definition": "clan name, identity"
},
{
    "word": "aliit (clan)",
    "pronunciation": "[ah-LEET]",
    "definition": "family"
},
{
    "word": "Aliit ori'shya tal'din",
    "pronunciation": "[Ah-LEET-or-EESH-yah-tal-DEEN]",
    "definition": "Family is more than blood. (Saying.)"
},
{
    "word": "Alor",
    "pronunciation": "[ah-LOR]",
    "definition": "Chancellor"
},
{
    "word": "alor",
    "pronunciation": "[ah-LOR]",
    "definition": "leader, chief, *officer*, constable, boss"
},
{
    "word": "alor'ad",
    "pronunciation": "[al-OHR-ahd]",
    "definition": "captain"
},
{
    "word": "alorir",
    "pronunciation": "[ah-LOR-eer]",
    "definition": "lead"
},
{
    "word": "aloriya",
    "pronunciation": "[alor-EE-yah]",
    "definition": "capital (lit. head city)"
},
{
    "word": "alor'uus",
    "pronunciation": "[AH-lor-OOS]",
    "definition": "corporal"
},
{
    "word": "al'verde",
    "pronunciation": "[AHL-vair-day]",
    "definition": "commander"
},
{
    "word": "am",
    "pronunciation": "[ahm]",
    "definition": "change"
},
{
    "word": "an",
    "pronunciation": "[ahn]",
    "definition": "all"
},
{
    "word": "anade",
    "pronunciation": "[ah-NAH-day]",
    "definition": "everyone, everybody"
},
{
    "word": "anay",
    "pronunciation": "[AH-nay]",
    "definition": "every"
},
{
    "word": "ani",
    "pronunciation": "[AH-nee]",
    "definition": "total, complete"
},
{
    "word": "aninari",
    "pronunciation": "[ah-nee-nah-ree]",
    "definition": "result (lit. completed action)"
},
{
    "word": "aran",
    "pronunciation": "[AH-ran]",
    "definition": "guard"
},
{
    "word": "aranar",
    "pronunciation": "[ah-RAH-nar]",
    "definition": "defend"
},
{
    "word": "araniik",
    "pronunciation": "[ah-RAHN-eek]",
    "definition": "cordon"
},
{
    "word": "aranov",
    "pronunciation": "[AH-rah-nov]",
    "definition": "defense"
},
{
    "word": "ara'novor",
    "pronunciation": "[ah-RAH-nov]",
    "definition": "approach, stand in the way off, block"
},
{
    "word": "ara'novor",
    "pronunciation": "[AH-rah-NO-vor]",
    "definition": "obstruct, defend, blockade"
},
{
    "word": "arasuum",
    "pronunciation": "[ah-RAH-soom]",
    "definition": "stagnation,"
},
{
    "word": "arasuumir",
    "pronunciation": "[ah-rah-soo-MEER]",
    "definition": "stagnate, remain the same"
},
{
    "word": "arasuum'la",
    "pronunciation": "[ah-ra-SOOM-lah]",
    "definition": "unchanging, stagnant"
},
{
    "word": "arpat",
    "pronunciation": "[AR-pat]",
    "definition": "seed"
},
{
    "word": "aru'e",
    "pronunciation": "[ah-ROO-ay]",
    "definition": "enemy (noun)"
},
{
    "word": "aru'ela",
    "pronunciation": "[AH-roo-AY-la]",
    "definition": "hostile, enemy (adj)"
},
{
    "word": "aruetii",
    "pronunciation": "[ah-roo-AY-tee]",
    "definition": "traitor, foreigner, outsider"
},
{
    "word": "aruetiise",
    "pronunciation": "[ah-roo-ay-TEE-say]",
    "definition": "traitors, foreigners, outsiders"
},
{
    "word": "aruetyc",
    "pronunciation": "[AH-roo-eh-TEESH]",
    "definition": "traitorous"
},
{
    "word": "as...as",
    "pronunciation": "[sah]",
    "definition": "as, like (comparative)"
},
{
    "word": "ash'ad",
    "pronunciation": "[AH-shad]",
    "definition": "someone else"
},
{
    "word": "ash'amur",
    "pronunciation": "[keer-AH-moor]",
    "definition": "die (esp. violently in battle)"
},
{
    "word": "ashi",
    "pronunciation": "[AH-shee]",
    "definition": "other"
},
{
    "word": "Ashnar...",
    "pronunciation": "[AHSH-nar]",
    "definition": "Someone has (done) - can be followed by a noun or a verb"
},
{
    "word": "ast",
    "pronunciation": "[ast]",
    "definition": "itself"
},
{
    "word": "ast'ehut",
    "pronunciation": "[ast-teh-HUUT]",
    "definition": "fat"
},
{
    "word": "at",
    "pronunciation": "[aht]",
    "definition": "to (direction, movement)"
},
{
    "word": "at",
    "pronunciation": "[aht]",
    "definition": "towards, at (motion), to"
},
{
    "word": "atin",
    "pronunciation": "[ah-TEEN]",
    "definition": "stubborn, tenacious, capable of endurance"
},
{
    "word": "atiniir",
    "pronunciation": "[ah-teen-EER]",
    "definition": "endure, to put up with, to *take it*"
},
{
    "word": "atin'la",
    "pronunciation": "[ah-TEEN-la]",
    "definition": "tough"
}]