[
    {
       "word": "ra",
       "pronunciation": "[rah]",
       "definition": "or"
    },
    {
       "word": "racin",
       "pronunciation": "[ray-SEEN]",
       "definition": "pale"
    },
    {
       "word": "ramaanar",
       "pronunciation": "[rah-mahn-ARR]",
       "definition": "die, general term"
    },
    {
       "word": "ramaanla",
       "pronunciation": "[rah-MAHN-lah]",
       "definition": "mortal (in the sense of fallible or vulnerable)"
    },
    {
       "word": "ram'ika",
       "pronunciation": "[rah-MEE-kah]",
       "definition": "raid"
    },
    {
       "word": "ramikad",
       "pronunciation": "[RAH-mee-KAHD]",
       "definition": "commando"
    },
    {
       "word": "ramikadyc",
       "pronunciation": "[RAH-mee-KAHD-eesh]",
       "definition": "commando state of mind - an attitude that he/ she can do anything, endure anything, and achieve the objective. A blend of complete confidence and extreme tenacity instilled in special forces during training. Can also be used informally to describe a determined, focused person."
    },
    {
       "word": "ram'or",
       "pronunciation": "[RAHM-ohr]",
       "definition": "attack, beseige"
    },
    {
       "word": "ramorla",
       "pronunciation": "[rah-MOR-lah]",
       "definition": "besieged"
    },
    {
       "word": "ram'ser",
       "pronunciation": "[RAM-sair]",
       "definition": "sniper, marksman"
    },
    {
       "word": "rang",
       "pronunciation": "[rahng]",
       "definition": "ash"
    },
    {
       "word": "Rangir!",
       "pronunciation": "[RAN-geer]",
       "definition": "To hell with it!"
    },
    {
       "word": "ranov'la",
       "pronunciation": "[rah-NOHV-lah]",
       "definition": "secret"
    },
    {
       "word": "ratiin",
       "pronunciation": "[RAH-teen]",
       "definition": "always"
    },
    {
       "word": "rayshe'a",
       "pronunciation": "[ray-SHEE-ah]",
       "definition": "five"
    },
    {
       "word": "raysh'olan",
       "pronunciation": "[RAYSH-oh-lahn]",
       "definition": "five hundred"
    },
    {
       "word": "ray'ture",
       "pronunciation": "[ray-TOOR-ay]",
       "definition": "week"
    },
    {
       "word": "redalur",
       "pronunciation": "[red-AH-loor]",
       "definition": "dance (verb)"
    },
    {
       "word": "rejorhaa'ir",
       "pronunciation": "[ree-JOR-har-EER]",
       "definition": "tell"
    },
    {
       "word": "resol",
       "pronunciation": "[reh-SOL]",
       "definition": "six"
    },
    {
       "word": "Resol'nare",
       "pronunciation": "[RAY-sol NAH-ray]",
       "definition": "Six Actions, the tenets of Mando life"
    },
    {
       "word": "ret",
       "pronunciation": "[rayt]",
       "definition": "Perhaps, maybe"
    },
    {
       "word": "Ret'!",
       "pronunciation": "[rayt]",
       "definition": "Bye! See you!"
    },
    {
       "word": "ret'lini.",
       "pronunciation": "[Rayt-LEE-nee]",
       "definition": "just in case (colloquial - Mandos are cautious and always have a plan B)"
    },
    {
       "word": "Ret'urcye mhi",
       "pronunciation": "[ray-TOOR-shay-MEE]",
       "definition": "Goodbye - lit. *Maybe we'll meet again*"
    },
    {
       "word": "ret'yc",
       "pronunciation": "[RET-eesh]",
       "definition": "possible"
    },
    {
       "word": "riduur",
       "pronunciation": "[REE-door]",
       "definition": "partner, spouse, husband, wife"
    },
    {
       "word": "riduurok",
       "pronunciation": "[ree-DOO-rok]",
       "definition": "love bond, specifically between spouses - marriage agreement"
    },
    {
       "word": "riye",
       "pronunciation": "[REE-yay]",
       "definition": "favor, benefit, good turn"
    },
    {
       "word": "rohak",
       "pronunciation": "[RO-hahk]",
       "definition": "defeat"
    },
    {
       "word": "rohakar",
       "pronunciation": "[ro-ha-KAR]",
       "definition": "defeat (verb)"
    },
    {
       "word": "rol'eta",
       "pronunciation": "[ROHL-ay-tah]",
       "definition": "sixty"
    },
    {
       "word": "ru, r'",
       "pronunciation": "[roo]",
       "definition": "past tense prefix"
    },
    {
       "word": "rud",
       "pronunciation": "[rood]",
       "definition": "around"
    },
    {
       "word": "rugam",
       "pronunciation": "[ROO-gahm]",
       "definition": "sphere, ball"
    },
    {
       "word": "runi",
       "pronunciation": "[roo-NEE]",
       "definition": "soul (poetic only)"
    },
    {
       "word": "rusur",
       "pronunciation": "[roo-SOOR]",
       "definition": "land, ships or troops"
    },
    {
       "word": "ruug",
       "pronunciation": "[roog]",
       "definition": "old age"
    },
    {
       "word": "ruug'la",
       "pronunciation": "[ROOG-lah]",
       "definition": "old"
    },
    {
       "word": "ruus",
       "pronunciation": "[roos]",
       "definition": "rock"
    },
    {
       "word": "ruusaan",
       "pronunciation": "[roo-SAHN]",
       "definition": "reliable one (popular female name)"
    },
    {
       "word": "ruusaanyc",
       "pronunciation": "[roo-SAHN-eesh]",
       "definition": "reliable, trustworthy"
    },
    {
       "word": "ruusaar",
       "pronunciation": "[ROO-sahr]",
       "definition": "foundation"
    },
    {
       "word": "ruus'alor",
       "pronunciation": "[ROOS-ahl-or]",
       "definition": "sergeant"
    },
    {
       "word": "ruyot",
       "pronunciation": "[ROO-yot]",
       "definition": "the past, history"
    }
 ]