[
    {
       "word": "yacur",
       "pronunciation": "[YAH-soor]",
       "definition": "flush out"
    },
    {
       "word": "ya'gai",
       "pronunciation": "[YAH-guy]",
       "definition": "bowl"
    },
    {
       "word": "yai",
       "pronunciation": "[yay]",
       "definition": "belly, womb"
    },
    {
       "word": "yaihadla",
       "pronunciation": "[yai-HAHD-lah]",
       "definition": "pregnant"
    },
    {
       "word": "yaihi'l",
       "pronunciation": "[YAH-heel]",
       "definition": "full"
    },
    {
       "word": "yaim",
       "pronunciation": "[yaym]",
       "definition": "home"
    },
    {
       "word": "yaimi",
       "pronunciation": "[yay-MEE]",
       "definition": "neighbor"
    },
    {
       "word": "yaim'la",
       "pronunciation": "[YAYM`la]",
       "definition": "comfortable, familiar, sense of *at home*. Can also mean local to the speaker."
    },
    {
       "word": "yaim'ol",
       "pronunciation": "[yai-MOHL]",
       "definition": "return, homecoming"
    },
    {
       "word": "yaimpar",
       "pronunciation": "[yay-EEM-par]",
       "definition": "return"
    },
    {
       "word": "yai'yai",
       "pronunciation": "[YAY-aye]",
       "definition": "*richly nourishing* - peculiarly Mandalorian description of dense, high-calorie food, of great importance to people dependent on highly portable field rations"
    },
    {
       "word": "yaiyai'yc",
       "pronunciation": "[yai-YAI-eesh]",
       "definition": "bloated, satisfied"
    },
    {
       "word": "yamika",
       "pronunciation": "[yah-MEE-kah]",
       "definition": "room, chamber"
    },
    {
       "word": "yilad",
       "pronunciation": "[yee-LAHD]",
       "definition": "array (noun)"
    },
    {
       "word": "yustapir",
       "pronunciation": "[YOOST-ah-PEER]",
       "definition": "river (lit: water road)"
    },
    {
       "word": "yustarud",
       "pronunciation": "[YOOST-arood]",
       "definition": "perimeter"
    }
 ]